Metadata-Version: 1.0
Name: Bayesian1990-model
Version: 3.0
Summary: Linear Regression From Scratch
Home-page: UNKNOWN
Author: Alessio Polymeropoulos
Author-email: polymeropoulos@hotmail.com
License: UNKNOWN
Platform: UNKNOWN
